testagon/__init__.py
testagon/__main__.py
testagon/cli.py
testagon/critic.py
testagon/generate_invariants.py
testagon/logger.py
testagon/unit_tests.py
testagon/util.py
testagon-0.1.0.dist-info/METADATA
testagon-0.1.0.dist-info/WHEEL
testagon-0.1.0.dist-info/entry_points.txt
testagon-0.1.0.dist-info/top_level.txt
testagon-0.1.0.dist-info/RECORD
