Metadata-Version: 2.1
Name: testagon
Version: 0.1.0
Summary: Automated invariant detection and test case generation with LLMs
Requires-Python: >=3.9
Requires-Dist: openai
Requires-Dist: libcst
Requires-Dist: platformdirs
Requires-Dist: pytest>=8.3.3
Requires-Dist: pytest-json-report
Requires-Dist: colorama>=0.4.6
